cmh/__build__
cmh/__init__.py
cmh/_version.py
cmh/cmh.py
tests/__init__.py
CMH-1.0.1.dist-info/LICENSE
CMH-1.0.1.dist-info/METADATA
CMH-1.0.1.dist-info/WHEEL
CMH-1.0.1.dist-info/top_level.txt
CMH-1.0.1.dist-info/RECORD
