Metadata-Version: 2.1
Name: CMH
Version: 1.0.1
Summary: Cochran-Mantel-Haenzsel Chi2 Test
Home-page: https://github.com/mellesies/cmh
Author: Melle Sieswerda
Author-email: m.sieswerda@iknl.nl
License: UNKNOWN
Platform: UNKNOWN
Classifier: Programming Language :: Python :: 3
Classifier: License :: OSI Approved :: MIT License
Classifier: Operating System :: OS Independent
Requires-Python: >= 3.6
Requires-Dist: numpy (>=1.18)
Requires-Dist: pandas (>=1)
Requires-Dist: scikit-learn
